{
  "id": "http://w3id.org/openeduhub/vocabs/oehTopics/3be14c5d-d33a-45a5-b418-762a88704aaa",
  "type": "Concept",
  "followers": "https://test.skohub.io/followers?subject=w3id.org%2Fopeneduhub%2Fvocabs%2FoehTopics%2F3be14c5d-d33a-45a5-b418-762a88704aaa",
  "inbox": "https://test.skohub.io/inbox?target=w3id.org%2Fopeneduhub%2Fvocabs%2FoehTopics%2F3be14c5d-d33a-45a5-b418-762a88704aaa",
  "prefLabel": {
    "de": "Vergangenes Material del mes"
  },
  "definition": {
    "de": "Das hatten wir schon"
  },
  "broader": {
    "id": "http://w3id.org/openeduhub/vocabs/oehTopics/e2dadcd8-4180-48bd-b349-58eb146bea1d",
    "prefLabel": {
      "de": "Materiales del mes  |  Startseite ES"
    }
  },
  "inScheme": {
    "id": "http://w3id.org/openeduhub/vocabs/oeh-topics/5e40e372-735c-4b17-bbf7-e827a5702b57",
    "title": {
      "de": "Taxonomie von Lehrplanthemen"
    }
  },
  "@context": {
    "id": "@id",
    "type": "@type",
    "@vocab": "http://www.w3.org/2004/02/skos/core#",
    "xsd": "http://www.w3.org/2001/XMLSchema#",
    "dct": "http://purl.org/dc/terms/",
    "schema": "http://schema.org/",
    "vann": "http://purl.org/vocab/vann/",
    "title": {
      "@id": "dct:title",
      "@container": "@language"
    },
    "description": {
      "@id": "dct:description",
      "@container": "@language"
    },
    "issued": {
      "@id": "dct:issued",
      "@type": "xsd:date"
    },
    "created": {
      "@id": "dct:created",
      "@type": "xsd:date"
    },
    "modified": {
      "@id": "dct:modified",
      "@type": "xsd:date"
    },
    "creator": "dct:creator",
    "publisher": "dct:publisher",
    "preferredNamespacePrefix": "vann:preferredNamespacePrefix",
    "preferredNamespaceUri": "vann:preferredNamespaceUri",
    "isBasedOn": "schema:isBasedOn",
    "source": "dct:source",
    "prefLabel": {
      "@container": "@language"
    },
    "altLabel": {
      "@container": "@language"
    },
    "definition": {
      "@container": "@language"
    },
    "scopeNote": {
      "@container": "@language"
    },
    "note": {
      "@container": "@language"
    },
    "notation": {
      "@container": "@set"
    },
    "narrower": {
      "@container": "@set"
    },
    "relatedMatch": {
      "@container": "@set"
    },
    "narrowerTransitive": {
      "@container": "@set"
    },
    "broaderTransitive": {
      "@container": "@set"
    }
  }
}